{
  "schemaVersion": 1,
  "id": "autochatmod",
  "version": "${version}",
  "name": "AutoChatMod",
  "description": "A mod to monitor and flag chat messages for spam or inappropriate content.",
  "authors": ["7gtz"],
  "contact": {},
  "license": "MIT",
  "environment": "client",
  "entrypoints": {
    "client": [
      "sevengtz.autochatmod.AutoChatMod"
    ],
    "modmenu": [
      "sevengtz.autochatmod.ModMenuIntegration"
    ]
  },
  "depends": {
    "minecraft": "~1.21.4",
    "fabricloader": ">=0.17.2",
    "fabric-api": "*",
    "modmenu": ">=12.0.0",
    "cloth-config": ">=15.0.140"
  }
}